tests/__init__.py
tests/models.py
tests/settings.py
tests/urls.py
tests/migrations/0001_initial.py
tests/migrations/0002_auto_20200625_0434.py
tests/migrations/__init__.py
tests/tests/__init__.py
tests/tests/test_duplicates.py
tests/tests/test_views.py
wagtail_image_import/__init__.py
wagtail_image_import/models.py
wagtail_image_import/urls.py
wagtail_image_import/utils.py
wagtail_image_import/views.py
wagtail_image_import/wagtail_hooks.py
wagtail_image_import/migrations/0001_create_import_permission.py
wagtail_image_import/migrations/0002_driveidmapping.py
wagtail_image_import/migrations/__init__.py
wagtail_image_import/static/wagtail_image_import/css/import.css
wagtail_image_import/static/wagtail_image_import/js/importer.js
wagtail_image_import/templates/wagtail_image_import/edit_form.html
wagtail_image_import/templates/wagtail_image_import/import.html
wagtail_image_import/templates/wagtail_image_import/includes/import_dropdown.html
wagtail_image_import/templates/wagtailimages/images/index.html
wagtail_image_import/templatetags/__init__.py
wagtail_image_import/templatetags/wagtail_image_import_tags.py
wagtail_image_import-0.1.1.dist-info/METADATA
wagtail_image_import-0.1.1.dist-info/WHEEL
wagtail_image_import-0.1.1.dist-info/top_level.txt
wagtail_image_import-0.1.1.dist-info/RECORD
