Metadata-Version: 2.1
Name: wagtail-image-import
Version: 0.1.1
Summary: Adds bulk image imports from Google Drive to the Wagtail Admin
Home-page: https://github.com/jacobtoppm/wagtail-image-import/
Author: Jacob Topp-Mugglestone
Author-email: jacobtm3@googlemail.com
License: UNKNOWN
Platform: UNKNOWN
Classifier: Programming Language :: Python :: 3
Classifier: License :: OSI Approved :: MIT License
Classifier: Operating System :: OS Independent
Requires-Python: >=3.6
Requires-Dist: wagtail (>=2.12)
